MANIFEST.in
README.txt
setup.cfg
setup.py
collective/__init__.py
collective.collage.nested.egg-info/PKG-INFO
collective.collage.nested.egg-info/SOURCES.txt
collective.collage.nested.egg-info/dependency_links.txt
collective.collage.nested.egg-info/entry_points.txt
collective.collage.nested.egg-info/namespace_packages.txt
collective.collage.nested.egg-info/not-zip-safe
collective.collage.nested.egg-info/requires.txt
collective.collage.nested.egg-info/top_level.txt
collective/collage/__init__.py
collective/collage/nested/__init__.py
collective/collage/nested/configure.zcml
collective/collage/nested/patch.py
collective/collage/nested/rebuild_i18n.sh
collective/collage/nested/browser/__init__.py
collective/collage/nested/browser/configure.zcml
collective/collage/nested/browser/views.py
collective/collage/nested/browser/css/collage.css
collective/collage/nested/browser/templates/nested_content.pt
collective/collage/nested/browser/templates/nested_full.pt
collective/collage/nested/docs/browser.txt
collective/collage/nested/locales/collective.collage.nested.pot
collective/collage/nested/locales/en/LC_MESSAGES/collective.collage.nested.mo
collective/collage/nested/locales/en/LC_MESSAGES/collective.collage.nested.po
collective/collage/nested/locales/es/LC_MESSAGES/collective.collage.nested.mo
collective/collage/nested/locales/es/LC_MESSAGES/collective.collage.nested.po
collective/collage/nested/profiles/default/cssregistry.xml
collective/collage/nested/tests/__init__.py
collective/collage/nested/tests/base.py
collective/collage/nested/tests/test_doctest.py
docs/AUTHORS.txt
docs/HISTORY.txt
docs/INSTALL.txt
docs/LICENSE.GPL
docs/LICENSE.txt