Metadata-Version: 1.0
Name: collective.collage.nested
Version: 1.0
Summary: Display a nested Collage inside Collage
Home-page: http://svn.plone.org/svn/collective/Products.Collage/addons/collective.collage.nested/
Author: Marcos F. Romero
Author-email: marcos.romero {at} inter-cultura {dot} com
License: GPL
Platform: UNKNOWN
Classifier: Framework :: Plone
Classifier: Programming Language :: Python
